mappi/__init__.py
mappi/__main__.py
mappi/cli.py
mappi/config.py
mappi/data/config-basic.yml
mappi/data/config-default.yml
mappi/data/config-full.yml
mappi/handlers.py
mappi/schema.py
mappi/server.py
mappi/utils.py
mappi-0.6.0.dist-info/entry_points.txt
mappi-0.6.0.dist-info/WHEEL
mappi-0.6.0.dist-info/METADATA
mappi-0.6.0.dist-info/RECORD
