Metadata-Version: 2.1
Name: mappi
Version: 0.6.0
Summary: Spin up webserver from a yaml config file
License: MIT
Author: Misha Behersky
Author-email: bmwant@gmail.com
Requires-Python: >=3.10,<4.0
Classifier: License :: OSI Approved :: MIT License
Classifier: Programming Language :: Python :: 3
Classifier: Programming Language :: Python :: 3.10
Classifier: Programming Language :: Python :: 3.11
Requires-Dist: PyYAML (>=6.0,<7.0)
Requires-Dist: fastapi (>=0.87.0,<0.88.0)
Requires-Dist: rich (>=12.6.0,<13.0.0)
Requires-Dist: uvicorn (>=0.20.0,<0.21.0)
